django_unused2/__init__.py
django_unused2/check_template_util.py
django_unused2/dataclasses.py
django_unused2/file_finder.py
django_unused2/filter.py
django_unused2/graph.py
django_unused2/management/__init__.py
django_unused2/management/commands/__init__.py
django_unused2/management/commands/check_templates.py
django_unused2/management/commands/unused.py
django_unused2/output.py
django_unused2/settings.py
django_unused2/template_util.py
django_unused2/tests/__init__.py
django_unused2/tests/test_admin_access.py
django_unused2-0.2.5.dist-info/METADATA
django_unused2-0.2.5.dist-info/WHEEL
django_unused2-0.2.5.dist-info/RECORD
