Metadata-Version: 2.1
Name: django_unused2
Version: 0.2.5
Summary: 
Author: Karel Hovorka
Author-email: git@karel-hovorka.eu
Requires-Python: >=3.9,<4.0
Classifier: Programming Language :: Python :: 3
Classifier: Programming Language :: Python :: 3.9
Classifier: Programming Language :: Python :: 3.10
Classifier: Programming Language :: Python :: 3.11
Classifier: Programming Language :: Python :: 3.12
Requires-Dist: Django (>=3.0)
Requires-Dist: colorama (>=0.4.6,<0.5.0)
